[
  {
    "code": "BTC",
    "name": "ビットコイン",
    "value": 70916,
    "previousValue": 71038,
    "unit": "USD",
    "source": "coingecko",
    "recordedAt": "2026-04-12T14:02:11.102Z"
  },
  {
    "code": "ETH",
    "name": "イーサリアム",
    "value": 2186.52,
    "previousValue": 2194.04,
    "unit": "USD",
    "source": "coingecko",
    "recordedAt": "2026-04-12T14:02:11.102Z"
  },
  {
    "code": "GOLD",
    "name": "金価格",
    "value": 4681.51,
    "previousValue": 4687.89,
    "unit": "USD/oz",
    "source": "coingecko",
    "recordedAt": "2026-04-12T14:02:11.102Z"
  },
  {
    "code": "USDJPY",
    "name": "ドル円",
    "value": 159.21,
    "previousValue": 159.21,
    "unit": "円",
    "source": "coingecko",
    "recordedAt": "2026-04-12T14:02:11.102Z"
  }
]