[
  {
    "category": "currency_finance",
    "score": 70,
    "level": "high",
    "summaryJa": "日本の株と国債市場が試練に直面していることや、ドル円の変動が金融市場に影響を及ぼす可能性がある。ただし、ビットコインやイーサリアムの価格は前回より上昇している。",
    "factorsJa": [
      "日本の株と国債市場の動向",
      "ドル円の変動",
      "ビットコインやイーサリアムの価格上昇"
    ],
    "assessedAt": "2026-05-10T04:04:14.269Z"
  },
  {
    "category": "geopolitics_supply_chain",
    "score": 82,
    "level": "critical",
    "summaryJa": "プーチン氏が北朝鮮軍に謝意を表明したことや、イギリス海軍が中東に駆逐艦を派遣する計画が地政学的緊張を高める可能性がある。ハンガリーの新首相がEUとの関係修復を目指すことにも注目される。",
    "factorsJa": [
      "プーチン氏の北朝鮮軍への謝意",
      "イギリス海軍の中東への駆逐艦派遣計画",
      "ハンガリーのEUとの関係修復"
    ],
    "assessedAt": "2026-05-10T04:04:14.269Z"
  },
  {
    "category": "technology",
    "score": 80,
    "level": "high",
    "summaryJa": "JICAが途上国の宇宙技術を支援する取り組みを始めたことや、高専卒の採用競争が激化していることから、技術協力や人材育成への影響が見られる。",
    "factorsJa": [
      "JICAの宇宙技術支援",
      "高専卒の採用競争の激化"
    ],
    "assessedAt": "2026-05-10T04:04:14.269Z"
  },
  {
    "category": "social_policy",
    "score": 75,
    "level": "high",
    "summaryJa": "ODAに民間マネーを導入する法律改正が進んでいないことから、経済開発への影響が懸念される。ただし、文化交流や観光への影響はあるものの、マクロ経済への直接的な影響は限定的である。",
    "factorsJa": [
      "ODAへの民間マネー導入の遅れ",
      "文化交流や観光への影響"
    ],
    "assessedAt": "2026-05-10T04:04:14.269Z"
  }
]