[
  {
    "category": "currency_finance",
    "score": 70,
    "level": "high",
    "summaryJa": "ドル円の変動は穏やかだが、FRBの金融政策変更の予想や原油価格の高騰が金融市場に影響を及ぼす可能性がある。",
    "factorsJa": [
      "FRBのFOMC",
      "原油価格の高騰",
      "ドル円の変動"
    ],
    "assessedAt": "2026-04-25T19:08:33.486Z"
  },
  {
    "category": "geopolitics_supply_chain",
    "score": 85,
    "level": "critical",
    "summaryJa": "米国とイランの協議が見送られたことやトランプ政権の対イラン協議の再開が見通せないため、地政学的な緊張が高まり、経済への影響が大きい。",
    "factorsJa": [
      "米国とイランの協議",
      "トランプ政権の対イラン協議",
      "地政学的な緊張"
    ],
    "assessedAt": "2026-04-25T19:08:33.486Z"
  },
  {
    "category": "technology",
    "score": 90,
    "level": "critical",
    "summaryJa": "AIエージェントの社会への導入やAI活用スキルの重要性が高まっており、企業や社会への影響が大きい。技術的な進歩も続いており、将来の産業や社会への影響が予想される。",
    "factorsJa": [
      "AIエージェントの社会への導入",
      "AI活用スキルの重要性",
      "技術的な進歩"
    ],
    "assessedAt": "2026-04-25T19:08:33.486Z"
  },
  {
    "category": "social_policy",
    "score": 75,
    "level": "high",
    "summaryJa": "消費者物価の変動や企業の社会的責任が問われる中、経済への影響が大きい。リユースやサステナビリティが注目される中、社会的な問題も重要視される。",
    "factorsJa": [
      "消費者物価の変動",
      "企業の社会的責任",
      "リユースやサステナビリティ"
    ],
    "assessedAt": "2026-04-25T19:08:33.486Z"
  }
]